<?xml version="1.0" encoding="UTF-8"?>
<!--Ajout XSLT-->
<?xml-stylesheet type="text/xsl" href="INTERBOB.xslt"?>
<!--Sample XML file for INTERBOB GA-->
<IBACDC:MessageAcquisitions xsi:schemaLocation="urn:IBACDC_V1 IBACDC.xsd" xmlns:xsi="http://www.w3.org/2001/XMLSchema-instance" xmlns:IBACDC="urn:IBACDC_V1">
	<DateHeure>2001-12-17T09:30:47Z</DateHeure>
	<ElementControleIntegrite></ElementControleIntegrite>
	<CorrespondantEmetteur>
		<Nom></Nom>
		<IdPartenaire>24</IdPartenaire>
		<CodePays>250</CodePays>
		<CodeBassin>502</CodeBassin>
	</CorrespondantEmetteur>
	<CorrespondantDestinataire>
		<Nom></Nom>
		<IdPartenaire>110</IdPartenaire>
		<CodePays>250</CodePays>
		<CodeBassin>502</CodeBassin>
	</CorrespondantDestinataire>
	<FormatMessage>
		<ReferenceNorme>IBACDC:MessageAcquisitions</ReferenceNorme>
		<VersionNorme>1.1:502.1</VersionNorme>
	</FormatMessage>
	<IdMessage>75</IdMessage>
	<ListeAcquisition>
		<OperationVente>
			<Date>2014-08-13</Date>
			<Heure>14:20:00.0Z</Heure>
			<IdOperation>1</IdOperation>
			<TypeOperationVente>1</TypeOperationVente>
			<CodeArticle></CodeArticle>
			<ElementControleIntegrite></ElementControleIntegrite>
			<EtatOperation>1</EtatOperation>
			<MontantOperation>99.10</MontantOperation>
			<MoyenPaiementPrincipal>3</MoyenPaiementPrincipal>
			<EquipementAcquisition>
				<IdEquipement>AAA-236B-----1</IdEquipement>
				<TypeEquipement>1</TypeEquipement>
				<IdFournisseurEquipement>
					<Nom>FOURNISSEUR</Nom>
					<Referentiel>6024</Referentiel>
					<IdentifiantDansReferentiel>930</IdentifiantDansReferentiel>
				</IdFournisseurEquipement>
				<ExploitantEquipement>
					<Nom>Exploitant</Nom>
					<IdPartenaire>1</IdPartenaire>
					<CodePays>250</CodePays>
					<CodeBassin>502</CodeBassin>
				</ExploitantEquipement>
			</EquipementAcquisition>
			<LieuDistribution>
				<IdLocalisation>1412</IdLocalisation>
				<ReferentielLocalisation>6012</ReferentielLocalisation>
				<Sens>Sens1</Sens>
				<Ligne>
					<TypeReferentiel>6012</TypeReferentiel>
					<IdLigne>12</IdLigne>
				</Ligne>
				<Course>
					<TypeReferentiel>6012</TypeReferentiel>
					<IdCourse>345</IdCourse>
				</Course>
				<LibelleLieuDistribution>GAREPARTDIEU0001</LibelleLieuDistribution>
				<VenteEmbarquee>0</VenteEmbarquee>
			</LieuDistribution>
			<Devise>EUR</Devise>
			<ObjetImplique>
				<Objet>
					<Description>
					</Description>
					<ApplicationUtilisee>
						<Distributeur>
							<IdPartenaire>000</IdPartenaire>
							<CodeBassin>000</CodeBassin>
						</Distributeur>
					</ApplicationUtilisee>					
				</Objet>
			</ObjetImplique>
			<AncienObjetImplique>
				<ProduitInstalle>
					<ReferenceProduit>
						<ProprietaireProduit>
							<Nom>Proprietaire</Nom>
							<IdPartenaire>4</IdPartenaire>
							<CodePays>250</CodePays>
							<CodeBassin>502</CodeBassin>
						</ProprietaireProduit>
						<IdProduit>110</IdProduit>
					</ReferenceProduit>
					<ReferenceProduitInstalle>
						<ExploitantVente>
							<Nom>OperateurVente</Nom>
							<IdPartenaire>3</IdPartenaire>
							<CodePays>250</CodePays>
							<CodeBassin>502</CodeBassin>
						</ExploitantVente>
						<IdProduitInstalle>234567892</IdProduitInstalle>
					</ReferenceProduitInstalle>
					<SoldeCompteur>
						<IdCompteur>1</IdCompteur>
						<QuantiteOperation>1</QuantiteOperation>
						<Solde>9</Solde>
					</SoldeCompteur>
					<ContrainteTemporelle>
						<TrancheCalendaire>
							<Dates>
								<JourDebut>0001-01-01</JourDebut>
								<JourFin>0001-01-01</JourFin>
							</Dates>
							<Autorise>false</Autorise>
						</TrancheCalendaire>
						<DureeValidite>P1Y2M3DT10H30M</DureeValidite>
					</ContrainteTemporelle>
					<FacteurTarifaireDeQualite>1</FacteurTarifaireDeQualite>
					<PrixDeVenteProduit>99.10</PrixDeVenteProduit>
					<ContrainteGeographique>
						<ContrainteParcours>
							<IndicateurContrainteChainage>2</IndicateurContrainteChainage>
							<PointArretDebut>
								<IdPointArret>103</IdPointArret>
								<TypeReferentiel>6003</TypeReferentiel>
							</PointArretDebut>
							<PointArretFin>
								<IdPointArret>112</IdPointArret>
								<TypeReferentiel>6003</TypeReferentiel>
							</PointArretFin>
						</ContrainteParcours>
						<ContrainteZonale>
							<IndicateurContrainteChainage>1</IndicateurContrainteChainage>
							<ZoneTarifaire>
								<TypeReferentiel>6024</TypeReferentiel>
								<IdZoneTarifaire>2</IdZoneTarifaire>
							</ZoneTarifaire>
						</ContrainteZonale>
					</ContrainteGeographique>
					<ApplicationUtilisee>
						<AID>A0000004040125000001000000000000</AID>
						<IdApplicationInstallee>3861754</IdApplicationInstallee>
						<Distributeur>
							<Nom>Distributeur1</Nom>
							<IdPartenaire>3</IdPartenaire>
							<CodePays>250</CodePays>
							<CodeBassin>502</CodeBassin>
						</Distributeur>
						<DateHeureFinValidite>2001-12-17T09:30:47Z</DateHeureFinValidite>
						<MatriceApplicationEnregistree>
							<IdMatriceApplication>001001</IdMatriceApplication>
							<TypeApplication>1</TypeApplication>
							<Proprietaire>
								<Nom>Proprietaire2</Nom>
								<IdPartenaire>2</IdPartenaire>
								<CodePays>250</CodePays>
								<CodeBassin>502</CodeBassin>
							</Proprietaire>
							<BassinsAcceptation>
								<CodePays>250</CodePays>
								<CodeBassin>502</CodeBassin>
							</BassinsAcceptation>
						</MatriceApplicationEnregistree>
					</ApplicationUtilisee>
					<SupportUtilise>
						<TypeSupport>00</TypeSupport>
						<CategorieSupport>00</CategorieSupport>
						<IdSupport>347645</IdSupport>
						<DateHeureEmission>2001-12-17T09:30:47Z</DateHeureEmission>
						<DateHeureFinValidite>2001-12-17T09:30:47Z</DateHeureFinValidite>
						<SoldeCompteur>
							<IdCompteur>00</IdCompteur>
							<QuantiteOperation>00</QuantiteOperation>
							<Solde>00</Solde>
						</SoldeCompteur>
						<ContratSupport>
							<TypeCommercialContrat>00</TypeCommercialContrat>
							<IdContrat>00</IdContrat>
							<ProfilCommercialContrat>
								<CodeProfilCommercialContrat></CodeProfilCommercialContrat>
								<DateDebutValidite>0001-01-01</DateDebutValidite>
								<DateFinValidite>0001-01-01</DateFinValidite>
								<DonneeComplementaire></DonneeComplementaire>
								<Proprietaire>
									<Nom></Nom>
									<IdPartenaire>000</IdPartenaire>
									<CodePays>000</CodePays>
									<CodeBassin>000</CodeBassin>
								</Proprietaire>
							</ProfilCommercialContrat>
							<ClientDetenteur>
								<IdClient>000</IdClient>
								<Nom></Nom>
								<Prenom></Prenom>
								<Titre>00</Titre>
								<DateNaissance>0001-01-01</DateNaissance>
								<TelephonePrive></TelephonePrive>
								<TelephoneTravail></TelephoneTravail>
								<Adresse>
									<NumVoie></NumVoie>
									<TypeVoie></TypeVoie>
									<LibelleVoie></LibelleVoie>
									<LigneAdresse>
										<NumLigne>1</NumLigne>
										<TexteLigne></TexteLigne>
									</LigneAdresse>
									<CodePostal></CodePostal>
									<CodePays>000</CodePays>
								</Adresse>
								<AdresseTravail>
									<NumVoie></NumVoie>
									<TypeVoie></TypeVoie>
									<LibelleVoie></LibelleVoie>
									<LigneAdresse>
										<NumLigne>1</NumLigne>
										<TexteLigne></TexteLigne>
									</LigneAdresse>
									<CodePostal></CodePostal>
									<CodePays>000</CodePays>
								</AdresseTravail>
								<CommunicationDonneesPersonnelles>true</CommunicationDonneesPersonnelles>
								<DateSaisie>0001-01-01</DateSaisie>
								<ProfilClient>
									<CodeProfil>00</CodeProfil>
									<DateDebutValiditeProfil>0001-01-01</DateDebutValiditeProfil>
									<DateFinValiditeProfil>0001-01-01</DateFinValiditeProfil>
									<CategorieSociale></CategorieSociale>
									<NiveaudEtudes></NiveaudEtudes>
									<Profession></Profession>
									<Sexe></Sexe>
									<TranchedAge></TranchedAge>
								</ProfilClient>
								<PartenaireReferent>
									<Nom></Nom>
									<IdPartenaire>000</IdPartenaire>
									<CodePays>000</CodePays>
									<CodeBassin>000</CodeBassin>
								</PartenaireReferent>
							</ClientDetenteur>
						</ContratSupport>
						<EmetteurSupportEnregistre>
							<Nom></Nom>
							<IdPartenaire>000</IdPartenaire>
							<CodePays>000</CodePays>
							<CodeBassin>000</CodeBassin>
						</EmetteurSupportEnregistre>
					</SupportUtilise>
					<ContratProduit>
						<TypeCommercialContrat>000</TypeCommercialContrat>
						<IdContrat>000</IdContrat>
						<ProfilCommercialContrat>
							<CodeProfilCommercialContrat></CodeProfilCommercialContrat>
							<DateDebutValidite>0001-01-01</DateDebutValidite>
							<DateFinValidite>0001-01-01</DateFinValidite>
							<DonneeComplementaire></DonneeComplementaire>
							<Proprietaire>
								<Nom></Nom>
								<IdPartenaire>000</IdPartenaire>
								<CodePays>000</CodePays>
								<CodeBassin>000</CodeBassin>
							</Proprietaire>
						</ProfilCommercialContrat>
						<ClientDetenteur>
							<IdClient>00</IdClient>
							<Nom></Nom>
							<Prenom></Prenom>
							<Titre>00</Titre>
							<DateNaissance>0001-01-01</DateNaissance>
							<TelephonePrive></TelephonePrive>
							<TelephoneTravail></TelephoneTravail>
							<Adresse>
								<NumVoie></NumVoie>
								<TypeVoie></TypeVoie>
								<LibelleVoie></LibelleVoie>
								<LigneAdresse>
									<NumLigne>1</NumLigne>
									<TexteLigne></TexteLigne>
								</LigneAdresse>
								<CodePostal></CodePostal>
								<CodePays>000</CodePays>
							</Adresse>
							<AdresseTravail>
								<NumVoie></NumVoie>
								<TypeVoie></TypeVoie>
								<LibelleVoie></LibelleVoie>
								<LigneAdresse>
									<NumLigne>1</NumLigne>
									<TexteLigne></TexteLigne>
								</LigneAdresse>
								<CodePostal></CodePostal>
								<CodePays>000</CodePays>
							</AdresseTravail>
							<CommunicationDonneesPersonnelles>true</CommunicationDonneesPersonnelles>
							<DateSaisie>0001-01-01</DateSaisie>
							<ProfilClient>
								<CodeProfil>00</CodeProfil>
								<DateDebutValiditeProfil>0001-01-01</DateDebutValiditeProfil>
								<DateFinValiditeProfil>0001-01-01</DateFinValiditeProfil>
								<CategorieSociale></CategorieSociale>
								<NiveaudEtudes></NiveaudEtudes>
								<Profession></Profession>
								<Sexe></Sexe>
								<TranchedAge></TranchedAge>
							</ProfilClient>
							<PartenaireReferent>
								<Nom></Nom>
								<IdPartenaire>000</IdPartenaire>
								<CodePays>000</CodePays>
								<CodeBassin>000</CodeBassin>
							</PartenaireReferent>
						</ClientDetenteur>
					</ContratProduit>
					<ContrainteLignes>
						<Transporteur>
							<Nom>Transporteur1</Nom>
							<IdPartenaire>165</IdPartenaire>
							<CodePays>250</CodePays>
							<CodeBassin>502</CodeBassin>
						</Transporteur>
						<LignePermise>
							<TypeReferentiel>6003</TypeReferentiel>
							<IdLigne>13</IdLigne>
						</LignePermise>
					</ContrainteLignes>
					<ContrainteGroupesLignes>
						<Transporteur>
							<Nom>Transporteur2</Nom>
							<IdPartenaire>2</IdPartenaire>
							<CodePays>250</CodePays>
							<CodeBassin>502</CodeBassin>
						</Transporteur>
						<GroupeDeLignesPermisPour>
							<Nom>Transporteur2</Nom>
							<TypeReferentiel>6002</TypeReferentiel>
							<IdGroupeDeLignes>1</IdGroupeDeLignes>
						</GroupeDeLignesPermisPour>
						<LigneInterditePour>
							<TypeReferentiel>6002</TypeReferentiel>
							<IdLigne>1</IdLigne>
						</LigneInterditePour>
					</ContrainteGroupesLignes>
					<ContrainteModale>
						<IdMode>1</IdMode>
					</ContrainteModale>
				</ProduitInstalle>
			</AncienObjetImplique>
		</OperationVente>
	</ListeAcquisition>
</IBACDC:MessageAcquisitions>
