<?xml version="1.0" encoding="UTF-8"?>
<!--Ajout XSLT-->
<?xml-stylesheet type="text/xsl" href="INTERBOB.xslt"?>
<!--Sample XML file for INTERBOB GA-->
<IBACBP:MessageAcquisitions xsi:schemaLocation="urn:IBACBP_V1 IBACBP.xsd" xmlns:xsi="http://www.w3.org/2001/XMLSchema-instance" xmlns:IBACBP="urn:IBACBP_V1">
	<DateHeure>2001-12-17T09:30:47Z</DateHeure>
	<ElementControleIntegrite>String</ElementControleIntegrite>
	<CorrespondantEmetteur>
		<Nom>normalizedString</Nom>
		<IdPartenaire>1</IdPartenaire>
		<CodePays>000</CodePays>
		<CodeBassin>000</CodeBassin>
	</CorrespondantEmetteur>
	<CorrespondantDestinataire>
		<Nom>normalizedString</Nom>
		<IdPartenaire>1</IdPartenaire>
		<CodePays>000</CodePays>
		<CodeBassin>000</CodeBassin>
	</CorrespondantDestinataire>
	<CorrespondantDestinataire>
		<Nom>normalizedString</Nom>
		<IdPartenaire>1</IdPartenaire>
		<CodePays>000</CodePays>
		<CodeBassin>000</CodeBassin>
	</CorrespondantDestinataire>
	<FormatMessage>
		<ReferenceNorme>normalizedString</ReferenceNorme>
		<VersionNorme>normalizedString</VersionNorme>
	</FormatMessage>
	<IdMessage>1</IdMessage>
	<ListeAcquisition>
		<OperationVente>
			<Date>1967-08-13</Date>
			<Heure>14:20:00.0Z</Heure>
			<IdOperation>1</IdOperation>
			<TypeOperationVente>1</TypeOperationVente>
			<CodeArticle>String</CodeArticle>
			<ElementControleIntegrite>String</ElementControleIntegrite>
			<EtatOperation>1</EtatOperation>
			<MontantOperation>0.0</MontantOperation>
			<MoyenPaiementPrincipal>1</MoyenPaiementPrincipal>
			<EquipementAcquisition>
				<IdEquipement>String</IdEquipement>
				<TypeEquipement>1</TypeEquipement>
				<IdFournisseurEquipement>
					<Nom>String</Nom>
					<Referentiel>String</Referentiel>
					<IdentifiantDansReferentiel>String</IdentifiantDansReferentiel>
				</IdFournisseurEquipement>
				<ExploitantEquipement>
					<Nom>normalizedString</Nom>
					<IdPartenaire>1</IdPartenaire>
					<CodePays>000</CodePays>
					<CodeBassin>000</CodeBassin>
				</ExploitantEquipement>
			</EquipementAcquisition>
			<LieuDistribution>
				<IdLocalisation>String</IdLocalisation>
				<ReferentielLocalisation>1</ReferentielLocalisation>
				<Sens>String</Sens>
				<Ligne>
					<TypeReferentiel>1</TypeReferentiel>
					<IdLigne>1</IdLigne>
				</Ligne>
				<Course>
					<TypeReferentiel>1</TypeReferentiel>
					<IdCourse>1</IdCourse>
				</Course>
				<LibelleLieuDistribution>String</LibelleLieuDistribution>
				<VenteEmbarquee>true</VenteEmbarquee>
			</LieuDistribution>
			<Devise>String</Devise>
			<ObjetImplique>
				<Objet>
					<Description></Description>
					<ApplicationUtilisee>
						<Distributeur>
							<IdPartenaire>000</IdPartenaire>
							<CodeBassin>000</CodeBassin>
						</Distributeur>
					</ApplicationUtilisee>
				</Objet>
			</ObjetImplique>
			<AncienObjetImplique>
				<ProduitInstalle>
					<ReferenceProduit>
						<ProprietaireProduit>
							<Nom>normalizedString</Nom>
							<IdPartenaire>1</IdPartenaire>
							<CodePays>000</CodePays>
							<CodeBassin>000</CodeBassin>
						</ProprietaireProduit>
						<IdProduit>1</IdProduit>
					</ReferenceProduit>
					<ReferenceProduitInstalle>
						<ExploitantVente>
							<Nom>normalizedString</Nom>
							<IdPartenaire>1</IdPartenaire>
							<CodePays>000</CodePays>
							<CodeBassin>000</CodeBassin>
						</ExploitantVente>
						<IdProduitInstalle>1</IdProduitInstalle>
					</ReferenceProduitInstalle>
					<SoldeCompteur>
						<IdCompteur>1</IdCompteur>
						<QuantiteOperation>0</QuantiteOperation>
						<Solde>0</Solde>
					</SoldeCompteur>
					<SoldeCompteur>
						<IdCompteur>1</IdCompteur>
						<QuantiteOperation>0</QuantiteOperation>
						<Solde>0</Solde>
					</SoldeCompteur>
					<ContrainteTemporelle>
						<TrancheHoraire>
							<HeureDeDebut>14:20:00.0Z</HeureDeDebut>
							<HeureDeFin>14:20:00.0Z</HeureDeFin>
							<Autorise>true</Autorise>
						</TrancheHoraire>
						<DureeValidite>P1Y2M3DT10H30M</DureeValidite>
					</ContrainteTemporelle>
					<ContrainteTemporelle>
						<TrancheHoraire>
							<HeureDeDebut>14:20:00.0Z</HeureDeDebut>
							<HeureDeFin>14:20:00.0Z</HeureDeFin>
							<Autorise>true</Autorise>
						</TrancheHoraire>
						<DureeValidite>P1Y2M3DT10H30M</DureeValidite>
					</ContrainteTemporelle>
					<FacteurTarifaireDeQualite>1</FacteurTarifaireDeQualite>
					<PrixDeVenteProduit>0.0</PrixDeVenteProduit>
					<ContrainteGeographique>
						<ContrainteParcours>
							<IndicateurContrainteChainage>0</IndicateurContrainteChainage>
							<PointArretDebut>
								<IdPointArret>String</IdPointArret>
								<TypeReferentiel>1</TypeReferentiel>
							</PointArretDebut>
							<PointArretFin>
								<IdPointArret>String</IdPointArret>
								<TypeReferentiel>1</TypeReferentiel>
							</PointArretFin>
						</ContrainteParcours>
						<ContrainteZonale>
							<IndicateurContrainteChainage>0</IndicateurContrainteChainage>
							<ZoneTarifaire>
								<TypeReferentiel>1</TypeReferentiel>
								<IdZoneTarifaire>1</IdZoneTarifaire>
							</ZoneTarifaire>
							<ZoneTarifaire>
								<TypeReferentiel>1</TypeReferentiel>
								<IdZoneTarifaire>1</IdZoneTarifaire>
							</ZoneTarifaire>
						</ContrainteZonale>
					</ContrainteGeographique>
					<ContrainteGeographique>
						<ContrainteParcours>
							<IndicateurContrainteChainage>0</IndicateurContrainteChainage>
							<PointArretDebut>
								<IdPointArret>String</IdPointArret>
								<TypeReferentiel>1</TypeReferentiel>
							</PointArretDebut>
							<PointArretFin>
								<IdPointArret>String</IdPointArret>
								<TypeReferentiel>1</TypeReferentiel>
							</PointArretFin>
						</ContrainteParcours>
						<ContrainteZonale>
							<IndicateurContrainteChainage>0</IndicateurContrainteChainage>
							<ZoneTarifaire>
								<TypeReferentiel>1</TypeReferentiel>
								<IdZoneTarifaire>1</IdZoneTarifaire>
							</ZoneTarifaire>
							<ZoneTarifaire>
								<TypeReferentiel>1</TypeReferentiel>
								<IdZoneTarifaire>1</IdZoneTarifaire>
							</ZoneTarifaire>
						</ContrainteZonale>
					</ContrainteGeographique>
					<ApplicationUtilisee>
						<AID>String</AID>
						<IdApplicationInstallee>String</IdApplicationInstallee>
						<Distributeur>
							<Nom>normalizedString</Nom>
							<IdPartenaire>1</IdPartenaire>
							<CodePays>000</CodePays>
							<CodeBassin>000</CodeBassin>
						</Distributeur>
						<DateHeureFinValidite>2001-12-17T09:30:47Z</DateHeureFinValidite>
						<MatriceApplicationEnregistree>
							<IdMatriceApplication>String</IdMatriceApplication>
							<TypeApplication>1</TypeApplication>
							<Proprietaire>
								<Nom>normalizedString</Nom>
								<IdPartenaire>1</IdPartenaire>
								<CodePays>000</CodePays>
								<CodeBassin>000</CodeBassin>
							</Proprietaire>
							<BassinsAcceptation>
								<CodePays>000</CodePays>
								<CodeBassin>000</CodeBassin>
								<CodeBassin>000</CodeBassin>
							</BassinsAcceptation>
							<BassinsAcceptation>
								<CodePays>000</CodePays>
								<CodeBassin>000</CodeBassin>
								<CodeBassin>000</CodeBassin>
							</BassinsAcceptation>
						</MatriceApplicationEnregistree>
					</ApplicationUtilisee>
					<SupportUtilise>
						<TypeSupport>1</TypeSupport>
						<CategorieSupport>1</CategorieSupport>
						<IdSupport>1</IdSupport>
						<DateHeureEmission>2001-12-17T09:30:47Z</DateHeureEmission>
						<DateHeureFinValidite>2001-12-17T09:30:47Z</DateHeureFinValidite>
						<SoldeCompteur>
							<IdCompteur>1</IdCompteur>
							<QuantiteOperation>0</QuantiteOperation>
							<Solde>0</Solde>
						</SoldeCompteur>
						<SoldeCompteur>
							<IdCompteur>1</IdCompteur>
							<QuantiteOperation>0</QuantiteOperation>
							<Solde>0</Solde>
						</SoldeCompteur>
						<ContratSupport>
							<TypeCommercialContrat>1</TypeCommercialContrat>
							<IdContrat>1</IdContrat>
							<ProfilCommercialContrat>
								<CodeProfilCommercialContrat>String</CodeProfilCommercialContrat>
								<DateDebutValidite>1967-08-13</DateDebutValidite>
								<DateFinValidite>1967-08-13</DateFinValidite>
								<DonneeComplementaire>String</DonneeComplementaire>
								<DonneeComplementaire>String</DonneeComplementaire>
								<Proprietaire>
									<Nom>normalizedString</Nom>
									<IdPartenaire>1</IdPartenaire>
									<CodePays>000</CodePays>
									<CodeBassin>000</CodeBassin>
								</Proprietaire>
							</ProfilCommercialContrat>
							<ClientDetenteur>
								<IdClient>1</IdClient>
								<Nom>normalizedString</Nom>
								<Prenom>normalizedString</Prenom>
								<Titre>1</Titre>
								<DateNaissance>1967-08-13</DateNaissance>
								<TelephonePrive>normalizedString</TelephonePrive>
								<TelephoneTravail>normalizedString</TelephoneTravail>
								<Adresse>
									<NumVoie>String</NumVoie>
									<TypeVoie>String</TypeVoie>
									<LibelleVoie>String</LibelleVoie>
									<LigneAdresse>
										<NumLigne>1</NumLigne>
										<TexteLigne>aaaaaaaaaaaaaaaaaaaaaaaaaaaaaaaa</TexteLigne>
									</LigneAdresse>
									<LigneAdresse>
										<NumLigne>1</NumLigne>
										<TexteLigne>aaaaaaaaaaaaaaaaaaaaaaaaaaaaaaaa</TexteLigne>
									</LigneAdresse>
									<CodePostal>String</CodePostal>
									<CodePays>000</CodePays>
								</Adresse>
								<AdresseTravail>
									<NumVoie>String</NumVoie>
									<TypeVoie>String</TypeVoie>
									<LibelleVoie>String</LibelleVoie>
									<LigneAdresse>
										<NumLigne>1</NumLigne>
										<TexteLigne>aaaaaaaaaaaaaaaaaaaaaaaaaaaaaaaa</TexteLigne>
									</LigneAdresse>
									<LigneAdresse>
										<NumLigne>1</NumLigne>
										<TexteLigne>aaaaaaaaaaaaaaaaaaaaaaaaaaaaaaaa</TexteLigne>
									</LigneAdresse>
									<CodePostal>String</CodePostal>
									<CodePays>000</CodePays>
								</AdresseTravail>
								<CommunicationDonneesPersonnelles>true</CommunicationDonneesPersonnelles>
								<DateSaisie>1967-08-13</DateSaisie>
								<ProfilClient>
									<CodeProfil>1</CodeProfil>
									<DateDebutValiditeProfil>1967-08-13</DateDebutValiditeProfil>
									<DateFinValiditeProfil>1967-08-13</DateFinValiditeProfil>
									<CategorieSociale>String</CategorieSociale>
									<NiveaudEtudes>String</NiveaudEtudes>
									<Profession>String</Profession>
									<Sexe>String</Sexe>
									<TranchedAge>String</TranchedAge>
								</ProfilClient>
								<ProfilClient>
									<CodeProfil>1</CodeProfil>
									<DateDebutValiditeProfil>1967-08-13</DateDebutValiditeProfil>
									<DateFinValiditeProfil>1967-08-13</DateFinValiditeProfil>
									<CategorieSociale>String</CategorieSociale>
									<NiveaudEtudes>String</NiveaudEtudes>
									<Profession>String</Profession>
									<Sexe>String</Sexe>
									<TranchedAge>String</TranchedAge>
								</ProfilClient>
								<PartenaireReferent>
									<Nom>normalizedString</Nom>
									<IdPartenaire>1</IdPartenaire>
									<CodePays>000</CodePays>
									<CodeBassin>000</CodeBassin>
								</PartenaireReferent>
							</ClientDetenteur>
						</ContratSupport>
						<EmetteurSupportEnregistre>
							<Nom>normalizedString</Nom>
							<IdPartenaire>1</IdPartenaire>
							<CodePays>000</CodePays>
							<CodeBassin>000</CodeBassin>
						</EmetteurSupportEnregistre>
					</SupportUtilise>
					<ContratProduit>
						<TypeCommercialContrat>1</TypeCommercialContrat>
						<IdContrat>1</IdContrat>
						<ProfilCommercialContrat>
							<CodeProfilCommercialContrat>String</CodeProfilCommercialContrat>
							<DateDebutValidite>1967-08-13</DateDebutValidite>
							<DateFinValidite>1967-08-13</DateFinValidite>
							<DonneeComplementaire>String</DonneeComplementaire>
							<DonneeComplementaire>String</DonneeComplementaire>
							<Proprietaire>
								<Nom>normalizedString</Nom>
								<IdPartenaire>1</IdPartenaire>
								<CodePays>000</CodePays>
								<CodeBassin>000</CodeBassin>
							</Proprietaire>
						</ProfilCommercialContrat>
						<ClientDetenteur>
							<IdClient>1</IdClient>
							<Nom>normalizedString</Nom>
							<Prenom>normalizedString</Prenom>
							<Titre>1</Titre>
							<DateNaissance>1967-08-13</DateNaissance>
							<TelephonePrive>normalizedString</TelephonePrive>
							<TelephoneTravail>normalizedString</TelephoneTravail>
							<Adresse>
								<NumVoie>String</NumVoie>
								<TypeVoie>String</TypeVoie>
								<LibelleVoie>String</LibelleVoie>
								<LigneAdresse>
									<NumLigne>1</NumLigne>
									<TexteLigne>aaaaaaaaaaaaaaaaaaaaaaaaaaaaaaaa</TexteLigne>
								</LigneAdresse>
								<LigneAdresse>
									<NumLigne>1</NumLigne>
									<TexteLigne>aaaaaaaaaaaaaaaaaaaaaaaaaaaaaaaa</TexteLigne>
								</LigneAdresse>
								<CodePostal>String</CodePostal>
								<CodePays>000</CodePays>
							</Adresse>
							<AdresseTravail>
								<NumVoie>String</NumVoie>
								<TypeVoie>String</TypeVoie>
								<LibelleVoie>String</LibelleVoie>
								<LigneAdresse>
									<NumLigne>1</NumLigne>
									<TexteLigne>aaaaaaaaaaaaaaaaaaaaaaaaaaaaaaaa</TexteLigne>
								</LigneAdresse>
								<LigneAdresse>
									<NumLigne>1</NumLigne>
									<TexteLigne>aaaaaaaaaaaaaaaaaaaaaaaaaaaaaaaa</TexteLigne>
								</LigneAdresse>
								<CodePostal>String</CodePostal>
								<CodePays>000</CodePays>
							</AdresseTravail>
							<CommunicationDonneesPersonnelles>true</CommunicationDonneesPersonnelles>
							<DateSaisie>1967-08-13</DateSaisie>
							<ProfilClient>
								<CodeProfil>1</CodeProfil>
								<DateDebutValiditeProfil>1967-08-13</DateDebutValiditeProfil>
								<DateFinValiditeProfil>1967-08-13</DateFinValiditeProfil>
								<CategorieSociale>String</CategorieSociale>
								<NiveaudEtudes>String</NiveaudEtudes>
								<Profession>String</Profession>
								<Sexe>String</Sexe>
								<TranchedAge>String</TranchedAge>
							</ProfilClient>
							<ProfilClient>
								<CodeProfil>1</CodeProfil>
								<DateDebutValiditeProfil>1967-08-13</DateDebutValiditeProfil>
								<DateFinValiditeProfil>1967-08-13</DateFinValiditeProfil>
								<CategorieSociale>String</CategorieSociale>
								<NiveaudEtudes>String</NiveaudEtudes>
								<Profession>String</Profession>
								<Sexe>String</Sexe>
								<TranchedAge>String</TranchedAge>
							</ProfilClient>
							<PartenaireReferent>
								<Nom>normalizedString</Nom>
								<IdPartenaire>1</IdPartenaire>
								<CodePays>000</CodePays>
								<CodeBassin>000</CodeBassin>
							</PartenaireReferent>
						</ClientDetenteur>
					</ContratProduit>
				</ProduitInstalle>
			</AncienObjetImplique>
		</OperationVente>
		<OperationVente>
			<Date>1967-08-13</Date>
			<Heure>14:20:00.0Z</Heure>
			<IdOperation>1</IdOperation>
			<TypeOperationVente>1</TypeOperationVente>
			<CodeArticle>String</CodeArticle>
			<ElementControleIntegrite>String</ElementControleIntegrite>
			<EtatOperation>1</EtatOperation>
			<MontantOperation>0.0</MontantOperation>
			<MoyenPaiementPrincipal>1</MoyenPaiementPrincipal>
			<EquipementAcquisition>
				<IdEquipement>String</IdEquipement>
				<TypeEquipement>1</TypeEquipement>
				<IdFournisseurEquipement>
					<Nom>String</Nom>
					<Referentiel>String</Referentiel>
					<IdentifiantDansReferentiel>String</IdentifiantDansReferentiel>
				</IdFournisseurEquipement>
				<ExploitantEquipement>
					<Nom>normalizedString</Nom>
					<IdPartenaire>1</IdPartenaire>
					<CodePays>000</CodePays>
					<CodeBassin>000</CodeBassin>
				</ExploitantEquipement>
			</EquipementAcquisition>
			<LieuDistribution>
				<IdLocalisation>String</IdLocalisation>
				<ReferentielLocalisation>1</ReferentielLocalisation>
				<Sens>String</Sens>
				<Ligne>
					<TypeReferentiel>1</TypeReferentiel>
					<IdLigne>1</IdLigne>
				</Ligne>
				<Course>
					<TypeReferentiel>1</TypeReferentiel>
					<IdCourse>1</IdCourse>
				</Course>
				<LibelleLieuDistribution>String</LibelleLieuDistribution>
				<VenteEmbarquee>true</VenteEmbarquee>
			</LieuDistribution>
			<Devise>String</Devise>
			<ObjetImplique>
				<ProduitInstalle>
					<ReferenceProduit>
						<ProprietaireProduit>
							<Nom>normalizedString</Nom>
							<IdPartenaire>1</IdPartenaire>
							<CodePays>000</CodePays>
							<CodeBassin>000</CodeBassin>
						</ProprietaireProduit>
						<IdProduit>1</IdProduit>
					</ReferenceProduit>
					<ReferenceProduitInstalle>
						<ExploitantVente>
							<Nom>normalizedString</Nom>
							<IdPartenaire>1</IdPartenaire>
							<CodePays>000</CodePays>
							<CodeBassin>000</CodeBassin>
						</ExploitantVente>
						<IdProduitInstalle>1</IdProduitInstalle>
					</ReferenceProduitInstalle>
					<SoldeCompteur>
						<IdCompteur>1</IdCompteur>
						<QuantiteOperation>0</QuantiteOperation>
						<Solde>0</Solde>
					</SoldeCompteur>
					<SoldeCompteur>
						<IdCompteur>1</IdCompteur>
						<QuantiteOperation>0</QuantiteOperation>
						<Solde>0</Solde>
					</SoldeCompteur>
					<ContrainteTemporelle>
						<TrancheHoraire>
							<HeureDeDebut>14:20:00.0Z</HeureDeDebut>
							<HeureDeFin>14:20:00.0Z</HeureDeFin>
							<Autorise>true</Autorise>
						</TrancheHoraire>
						<DureeValidite>P1Y2M3DT10H30M</DureeValidite>
					</ContrainteTemporelle>
					<ContrainteTemporelle>
						<TrancheHoraire>
							<HeureDeDebut>14:20:00.0Z</HeureDeDebut>
							<HeureDeFin>14:20:00.0Z</HeureDeFin>
							<Autorise>true</Autorise>
						</TrancheHoraire>
						<DureeValidite>P1Y2M3DT10H30M</DureeValidite>
					</ContrainteTemporelle>
					<FacteurTarifaireDeQualite>1</FacteurTarifaireDeQualite>
					<PrixDeVenteProduit>0.0</PrixDeVenteProduit>
					<ContrainteGeographique>
						<ContrainteParcours>
							<IndicateurContrainteChainage>0</IndicateurContrainteChainage>
							<PointArretDebut>
								<IdPointArret>String</IdPointArret>
								<TypeReferentiel>1</TypeReferentiel>
							</PointArretDebut>
							<PointArretFin>
								<IdPointArret>String</IdPointArret>
								<TypeReferentiel>1</TypeReferentiel>
							</PointArretFin>
						</ContrainteParcours>
						<ContrainteZonale>
							<IndicateurContrainteChainage>0</IndicateurContrainteChainage>
							<ZoneTarifaire>
								<TypeReferentiel>1</TypeReferentiel>
								<IdZoneTarifaire>1</IdZoneTarifaire>
							</ZoneTarifaire>
							<ZoneTarifaire>
								<TypeReferentiel>1</TypeReferentiel>
								<IdZoneTarifaire>1</IdZoneTarifaire>
							</ZoneTarifaire>
						</ContrainteZonale>
					</ContrainteGeographique>
					<ContrainteGeographique>
						<ContrainteParcours>
							<IndicateurContrainteChainage>0</IndicateurContrainteChainage>
							<PointArretDebut>
								<IdPointArret>String</IdPointArret>
								<TypeReferentiel>1</TypeReferentiel>
							</PointArretDebut>
							<PointArretFin>
								<IdPointArret>String</IdPointArret>
								<TypeReferentiel>1</TypeReferentiel>
							</PointArretFin>
						</ContrainteParcours>
						<ContrainteZonale>
							<IndicateurContrainteChainage>0</IndicateurContrainteChainage>
							<ZoneTarifaire>
								<TypeReferentiel>1</TypeReferentiel>
								<IdZoneTarifaire>1</IdZoneTarifaire>
							</ZoneTarifaire>
							<ZoneTarifaire>
								<TypeReferentiel>1</TypeReferentiel>
								<IdZoneTarifaire>1</IdZoneTarifaire>
							</ZoneTarifaire>
						</ContrainteZonale>
					</ContrainteGeographique>
					<ApplicationUtilisee>
						<AID>String</AID>
						<IdApplicationInstallee>String</IdApplicationInstallee>
						<Distributeur>
							<Nom>normalizedString</Nom>
							<IdPartenaire>1</IdPartenaire>
							<CodePays>000</CodePays>
							<CodeBassin>000</CodeBassin>
						</Distributeur>
						<DateHeureFinValidite>2001-12-17T09:30:47Z</DateHeureFinValidite>
						<MatriceApplicationEnregistree>
							<IdMatriceApplication>String</IdMatriceApplication>
							<TypeApplication>1</TypeApplication>
							<Proprietaire>
								<Nom>normalizedString</Nom>
								<IdPartenaire>1</IdPartenaire>
								<CodePays>000</CodePays>
								<CodeBassin>000</CodeBassin>
							</Proprietaire>
							<BassinsAcceptation>
								<CodePays>000</CodePays>
								<CodeBassin>000</CodeBassin>
								<CodeBassin>000</CodeBassin>
							</BassinsAcceptation>
							<BassinsAcceptation>
								<CodePays>000</CodePays>
								<CodeBassin>000</CodeBassin>
								<CodeBassin>000</CodeBassin>
							</BassinsAcceptation>
						</MatriceApplicationEnregistree>
					</ApplicationUtilisee>
					<SupportUtilise>
						<TypeSupport>1</TypeSupport>
						<CategorieSupport>1</CategorieSupport>
						<IdSupport>1</IdSupport>
						<DateHeureEmission>2001-12-17T09:30:47Z</DateHeureEmission>
						<DateHeureFinValidite>2001-12-17T09:30:47Z</DateHeureFinValidite>
						<SoldeCompteur>
							<IdCompteur>1</IdCompteur>
							<QuantiteOperation>0</QuantiteOperation>
							<Solde>0</Solde>
						</SoldeCompteur>
						<SoldeCompteur>
							<IdCompteur>1</IdCompteur>
							<QuantiteOperation>0</QuantiteOperation>
							<Solde>0</Solde>
						</SoldeCompteur>
						<ContratSupport>
							<TypeCommercialContrat>1</TypeCommercialContrat>
							<IdContrat>1</IdContrat>
							<ProfilCommercialContrat>
								<CodeProfilCommercialContrat>String</CodeProfilCommercialContrat>
								<DateDebutValidite>1967-08-13</DateDebutValidite>
								<DateFinValidite>1967-08-13</DateFinValidite>
								<DonneeComplementaire>String</DonneeComplementaire>
								<DonneeComplementaire>String</DonneeComplementaire>
								<Proprietaire>
									<Nom>normalizedString</Nom>
									<IdPartenaire>1</IdPartenaire>
									<CodePays>000</CodePays>
									<CodeBassin>000</CodeBassin>
								</Proprietaire>
							</ProfilCommercialContrat>
							<ClientDetenteur>
								<IdClient>1</IdClient>
								<Nom>normalizedString</Nom>
								<Prenom>normalizedString</Prenom>
								<Titre>1</Titre>
								<DateNaissance>1967-08-13</DateNaissance>
								<TelephonePrive>normalizedString</TelephonePrive>
								<TelephoneTravail>normalizedString</TelephoneTravail>
								<Adresse>
									<NumVoie>String</NumVoie>
									<TypeVoie>String</TypeVoie>
									<LibelleVoie>String</LibelleVoie>
									<LigneAdresse>
										<NumLigne>1</NumLigne>
										<TexteLigne>aaaaaaaaaaaaaaaaaaaaaaaaaaaaaaaa</TexteLigne>
									</LigneAdresse>
									<LigneAdresse>
										<NumLigne>1</NumLigne>
										<TexteLigne>aaaaaaaaaaaaaaaaaaaaaaaaaaaaaaaa</TexteLigne>
									</LigneAdresse>
									<CodePostal>String</CodePostal>
									<CodePays>000</CodePays>
								</Adresse>
								<AdresseTravail>
									<NumVoie>String</NumVoie>
									<TypeVoie>String</TypeVoie>
									<LibelleVoie>String</LibelleVoie>
									<LigneAdresse>
										<NumLigne>1</NumLigne>
										<TexteLigne>aaaaaaaaaaaaaaaaaaaaaaaaaaaaaaaa</TexteLigne>
									</LigneAdresse>
									<LigneAdresse>
										<NumLigne>1</NumLigne>
										<TexteLigne>aaaaaaaaaaaaaaaaaaaaaaaaaaaaaaaa</TexteLigne>
									</LigneAdresse>
									<CodePostal>String</CodePostal>
									<CodePays>000</CodePays>
								</AdresseTravail>
								<CommunicationDonneesPersonnelles>true</CommunicationDonneesPersonnelles>
								<DateSaisie>1967-08-13</DateSaisie>
								<ProfilClient>
									<CodeProfil>1</CodeProfil>
									<DateDebutValiditeProfil>1967-08-13</DateDebutValiditeProfil>
									<DateFinValiditeProfil>1967-08-13</DateFinValiditeProfil>
									<CategorieSociale>String</CategorieSociale>
									<NiveaudEtudes>String</NiveaudEtudes>
									<Profession>String</Profession>
									<Sexe>String</Sexe>
									<TranchedAge>String</TranchedAge>
								</ProfilClient>
								<ProfilClient>
									<CodeProfil>1</CodeProfil>
									<DateDebutValiditeProfil>1967-08-13</DateDebutValiditeProfil>
									<DateFinValiditeProfil>1967-08-13</DateFinValiditeProfil>
									<CategorieSociale>String</CategorieSociale>
									<NiveaudEtudes>String</NiveaudEtudes>
									<Profession>String</Profession>
									<Sexe>String</Sexe>
									<TranchedAge>String</TranchedAge>
								</ProfilClient>
								<PartenaireReferent>
									<Nom>normalizedString</Nom>
									<IdPartenaire>1</IdPartenaire>
									<CodePays>000</CodePays>
									<CodeBassin>000</CodeBassin>
								</PartenaireReferent>
							</ClientDetenteur>
						</ContratSupport>
						<EmetteurSupportEnregistre>
							<Nom>normalizedString</Nom>
							<IdPartenaire>1</IdPartenaire>
							<CodePays>000</CodePays>
							<CodeBassin>000</CodeBassin>
						</EmetteurSupportEnregistre>
					</SupportUtilise>
					<ContratProduit>
						<TypeCommercialContrat>1</TypeCommercialContrat>
						<IdContrat>1</IdContrat>
						<ProfilCommercialContrat>
							<CodeProfilCommercialContrat>String</CodeProfilCommercialContrat>
							<DateDebutValidite>1967-08-13</DateDebutValidite>
							<DateFinValidite>1967-08-13</DateFinValidite>
							<DonneeComplementaire>String</DonneeComplementaire>
							<DonneeComplementaire>String</DonneeComplementaire>
							<Proprietaire>
								<Nom>normalizedString</Nom>
								<IdPartenaire>1</IdPartenaire>
								<CodePays>000</CodePays>
								<CodeBassin>000</CodeBassin>
							</Proprietaire>
						</ProfilCommercialContrat>
						<ClientDetenteur>
							<IdClient>1</IdClient>
							<Nom>normalizedString</Nom>
							<Prenom>normalizedString</Prenom>
							<Titre>1</Titre>
							<DateNaissance>1967-08-13</DateNaissance>
							<TelephonePrive>normalizedString</TelephonePrive>
							<TelephoneTravail>normalizedString</TelephoneTravail>
							<Adresse>
								<NumVoie>String</NumVoie>
								<TypeVoie>String</TypeVoie>
								<LibelleVoie>String</LibelleVoie>
								<LigneAdresse>
									<NumLigne>1</NumLigne>
									<TexteLigne>aaaaaaaaaaaaaaaaaaaaaaaaaaaaaaaa</TexteLigne>
								</LigneAdresse>
								<LigneAdresse>
									<NumLigne>1</NumLigne>
									<TexteLigne>aaaaaaaaaaaaaaaaaaaaaaaaaaaaaaaa</TexteLigne>
								</LigneAdresse>
								<CodePostal>String</CodePostal>
								<CodePays>000</CodePays>
							</Adresse>
							<AdresseTravail>
								<NumVoie>String</NumVoie>
								<TypeVoie>String</TypeVoie>
								<LibelleVoie>String</LibelleVoie>
								<LigneAdresse>
									<NumLigne>1</NumLigne>
									<TexteLigne>aaaaaaaaaaaaaaaaaaaaaaaaaaaaaaaa</TexteLigne>
								</LigneAdresse>
								<LigneAdresse>
									<NumLigne>1</NumLigne>
									<TexteLigne>aaaaaaaaaaaaaaaaaaaaaaaaaaaaaaaa</TexteLigne>
								</LigneAdresse>
								<CodePostal>String</CodePostal>
								<CodePays>000</CodePays>
							</AdresseTravail>
							<CommunicationDonneesPersonnelles>true</CommunicationDonneesPersonnelles>
							<DateSaisie>1967-08-13</DateSaisie>
							<ProfilClient>
								<CodeProfil>1</CodeProfil>
								<DateDebutValiditeProfil>1967-08-13</DateDebutValiditeProfil>
								<DateFinValiditeProfil>1967-08-13</DateFinValiditeProfil>
								<CategorieSociale>String</CategorieSociale>
								<NiveaudEtudes>String</NiveaudEtudes>
								<Profession>String</Profession>
								<Sexe>String</Sexe>
								<TranchedAge>String</TranchedAge>
							</ProfilClient>
							<ProfilClient>
								<CodeProfil>1</CodeProfil>
								<DateDebutValiditeProfil>1967-08-13</DateDebutValiditeProfil>
								<DateFinValiditeProfil>1967-08-13</DateFinValiditeProfil>
								<CategorieSociale>String</CategorieSociale>
								<NiveaudEtudes>String</NiveaudEtudes>
								<Profession>String</Profession>
								<Sexe>String</Sexe>
								<TranchedAge>String</TranchedAge>
							</ProfilClient>
							<PartenaireReferent>
								<Nom>normalizedString</Nom>
								<IdPartenaire>1</IdPartenaire>
								<CodePays>000</CodePays>
								<CodeBassin>000</CodeBassin>
							</PartenaireReferent>
						</ClientDetenteur>
					</ContratProduit>
				</ProduitInstalle>
			</ObjetImplique>
			<AncienObjetImplique>
				<ProduitInstalle>
					<ReferenceProduit>
						<ProprietaireProduit>
							<Nom>normalizedString</Nom>
							<IdPartenaire>1</IdPartenaire>
							<CodePays>000</CodePays>
							<CodeBassin>000</CodeBassin>
						</ProprietaireProduit>
						<IdProduit>1</IdProduit>
					</ReferenceProduit>
					<ReferenceProduitInstalle>
						<ExploitantVente>
							<Nom>normalizedString</Nom>
							<IdPartenaire>1</IdPartenaire>
							<CodePays>000</CodePays>
							<CodeBassin>000</CodeBassin>
						</ExploitantVente>
						<IdProduitInstalle>1</IdProduitInstalle>
					</ReferenceProduitInstalle>
					<SoldeCompteur>
						<IdCompteur>1</IdCompteur>
						<QuantiteOperation>0</QuantiteOperation>
						<Solde>0</Solde>
					</SoldeCompteur>
					<SoldeCompteur>
						<IdCompteur>1</IdCompteur>
						<QuantiteOperation>0</QuantiteOperation>
						<Solde>0</Solde>
					</SoldeCompteur>
					<ContrainteTemporelle>
						<TrancheHoraire>
							<HeureDeDebut>14:20:00.0Z</HeureDeDebut>
							<HeureDeFin>14:20:00.0Z</HeureDeFin>
							<Autorise>true</Autorise>
						</TrancheHoraire>
						<DureeValidite>P1Y2M3DT10H30M</DureeValidite>
					</ContrainteTemporelle>
					<ContrainteTemporelle>
						<TrancheHoraire>
							<HeureDeDebut>14:20:00.0Z</HeureDeDebut>
							<HeureDeFin>14:20:00.0Z</HeureDeFin>
							<Autorise>true</Autorise>
						</TrancheHoraire>
						<DureeValidite>P1Y2M3DT10H30M</DureeValidite>
					</ContrainteTemporelle>
					<FacteurTarifaireDeQualite>1</FacteurTarifaireDeQualite>
					<PrixDeVenteProduit>0.0</PrixDeVenteProduit>
					<ContrainteGeographique>
						<ContrainteParcours>
							<IndicateurContrainteChainage>0</IndicateurContrainteChainage>
							<PointArretDebut>
								<IdPointArret>String</IdPointArret>
								<TypeReferentiel>1</TypeReferentiel>
							</PointArretDebut>
							<PointArretFin>
								<IdPointArret>String</IdPointArret>
								<TypeReferentiel>1</TypeReferentiel>
							</PointArretFin>
						</ContrainteParcours>
						<ContrainteZonale>
							<IndicateurContrainteChainage>0</IndicateurContrainteChainage>
							<ZoneTarifaire>
								<TypeReferentiel>1</TypeReferentiel>
								<IdZoneTarifaire>1</IdZoneTarifaire>
							</ZoneTarifaire>
							<ZoneTarifaire>
								<TypeReferentiel>1</TypeReferentiel>
								<IdZoneTarifaire>1</IdZoneTarifaire>
							</ZoneTarifaire>
						</ContrainteZonale>
					</ContrainteGeographique>
					<ContrainteGeographique>
						<ContrainteParcours>
							<IndicateurContrainteChainage>0</IndicateurContrainteChainage>
							<PointArretDebut>
								<IdPointArret>String</IdPointArret>
								<TypeReferentiel>1</TypeReferentiel>
							</PointArretDebut>
							<PointArretFin>
								<IdPointArret>String</IdPointArret>
								<TypeReferentiel>1</TypeReferentiel>
							</PointArretFin>
						</ContrainteParcours>
						<ContrainteZonale>
							<IndicateurContrainteChainage>0</IndicateurContrainteChainage>
							<ZoneTarifaire>
								<TypeReferentiel>1</TypeReferentiel>
								<IdZoneTarifaire>1</IdZoneTarifaire>
							</ZoneTarifaire>
							<ZoneTarifaire>
								<TypeReferentiel>1</TypeReferentiel>
								<IdZoneTarifaire>1</IdZoneTarifaire>
							</ZoneTarifaire>
						</ContrainteZonale>
					</ContrainteGeographique>
					<ApplicationUtilisee>
						<AID>String</AID>
						<IdApplicationInstallee>String</IdApplicationInstallee>
						<Distributeur>
							<Nom>normalizedString</Nom>
							<IdPartenaire>1</IdPartenaire>
							<CodePays>000</CodePays>
							<CodeBassin>000</CodeBassin>
						</Distributeur>
						<DateHeureFinValidite>2001-12-17T09:30:47Z</DateHeureFinValidite>
						<MatriceApplicationEnregistree>
							<IdMatriceApplication>String</IdMatriceApplication>
							<TypeApplication>1</TypeApplication>
							<Proprietaire>
								<Nom>normalizedString</Nom>
								<IdPartenaire>1</IdPartenaire>
								<CodePays>000</CodePays>
								<CodeBassin>000</CodeBassin>
							</Proprietaire>
							<BassinsAcceptation>
								<CodePays>000</CodePays>
								<CodeBassin>000</CodeBassin>
								<CodeBassin>000</CodeBassin>
							</BassinsAcceptation>
							<BassinsAcceptation>
								<CodePays>000</CodePays>
								<CodeBassin>000</CodeBassin>
								<CodeBassin>000</CodeBassin>
							</BassinsAcceptation>
						</MatriceApplicationEnregistree>
					</ApplicationUtilisee>
					<SupportUtilise>
						<TypeSupport>1</TypeSupport>
						<CategorieSupport>1</CategorieSupport>
						<IdSupport>1</IdSupport>
						<DateHeureEmission>2001-12-17T09:30:47Z</DateHeureEmission>
						<DateHeureFinValidite>2001-12-17T09:30:47Z</DateHeureFinValidite>
						<SoldeCompteur>
							<IdCompteur>1</IdCompteur>
							<QuantiteOperation>0</QuantiteOperation>
							<Solde>0</Solde>
						</SoldeCompteur>
						<SoldeCompteur>
							<IdCompteur>1</IdCompteur>
							<QuantiteOperation>0</QuantiteOperation>
							<Solde>0</Solde>
						</SoldeCompteur>
						<ContratSupport>
							<TypeCommercialContrat>1</TypeCommercialContrat>
							<IdContrat>1</IdContrat>
							<ProfilCommercialContrat>
								<CodeProfilCommercialContrat>String</CodeProfilCommercialContrat>
								<DateDebutValidite>1967-08-13</DateDebutValidite>
								<DateFinValidite>1967-08-13</DateFinValidite>
								<DonneeComplementaire>String</DonneeComplementaire>
								<DonneeComplementaire>String</DonneeComplementaire>
								<Proprietaire>
									<Nom>normalizedString</Nom>
									<IdPartenaire>1</IdPartenaire>
									<CodePays>000</CodePays>
									<CodeBassin>000</CodeBassin>
								</Proprietaire>
							</ProfilCommercialContrat>
							<ClientDetenteur>
								<IdClient>1</IdClient>
								<Nom>normalizedString</Nom>
								<Prenom>normalizedString</Prenom>
								<Titre>1</Titre>
								<DateNaissance>1967-08-13</DateNaissance>
								<TelephonePrive>normalizedString</TelephonePrive>
								<TelephoneTravail>normalizedString</TelephoneTravail>
								<Adresse>
									<NumVoie>String</NumVoie>
									<TypeVoie>String</TypeVoie>
									<LibelleVoie>String</LibelleVoie>
									<LigneAdresse>
										<NumLigne>1</NumLigne>
										<TexteLigne>aaaaaaaaaaaaaaaaaaaaaaaaaaaaaaaa</TexteLigne>
									</LigneAdresse>
									<LigneAdresse>
										<NumLigne>1</NumLigne>
										<TexteLigne>aaaaaaaaaaaaaaaaaaaaaaaaaaaaaaaa</TexteLigne>
									</LigneAdresse>
									<CodePostal>String</CodePostal>
									<CodePays>000</CodePays>
								</Adresse>
								<AdresseTravail>
									<NumVoie>String</NumVoie>
									<TypeVoie>String</TypeVoie>
									<LibelleVoie>String</LibelleVoie>
									<LigneAdresse>
										<NumLigne>1</NumLigne>
										<TexteLigne>aaaaaaaaaaaaaaaaaaaaaaaaaaaaaaaa</TexteLigne>
									</LigneAdresse>
									<LigneAdresse>
										<NumLigne>1</NumLigne>
										<TexteLigne>aaaaaaaaaaaaaaaaaaaaaaaaaaaaaaaa</TexteLigne>
									</LigneAdresse>
									<CodePostal>String</CodePostal>
									<CodePays>000</CodePays>
								</AdresseTravail>
								<CommunicationDonneesPersonnelles>true</CommunicationDonneesPersonnelles>
								<DateSaisie>1967-08-13</DateSaisie>
								<ProfilClient>
									<CodeProfil>1</CodeProfil>
									<DateDebutValiditeProfil>1967-08-13</DateDebutValiditeProfil>
									<DateFinValiditeProfil>1967-08-13</DateFinValiditeProfil>
									<CategorieSociale>String</CategorieSociale>
									<NiveaudEtudes>String</NiveaudEtudes>
									<Profession>String</Profession>
									<Sexe>String</Sexe>
									<TranchedAge>String</TranchedAge>
								</ProfilClient>
								<ProfilClient>
									<CodeProfil>1</CodeProfil>
									<DateDebutValiditeProfil>1967-08-13</DateDebutValiditeProfil>
									<DateFinValiditeProfil>1967-08-13</DateFinValiditeProfil>
									<CategorieSociale>String</CategorieSociale>
									<NiveaudEtudes>String</NiveaudEtudes>
									<Profession>String</Profession>
									<Sexe>String</Sexe>
									<TranchedAge>String</TranchedAge>
								</ProfilClient>
								<PartenaireReferent>
									<Nom>normalizedString</Nom>
									<IdPartenaire>1</IdPartenaire>
									<CodePays>000</CodePays>
									<CodeBassin>000</CodeBassin>
								</PartenaireReferent>
							</ClientDetenteur>
						</ContratSupport>
						<EmetteurSupportEnregistre>
							<Nom>normalizedString</Nom>
							<IdPartenaire>1</IdPartenaire>
							<CodePays>000</CodePays>
							<CodeBassin>000</CodeBassin>
						</EmetteurSupportEnregistre>
					</SupportUtilise>
					<ContratProduit>
						<TypeCommercialContrat>1</TypeCommercialContrat>
						<IdContrat>1</IdContrat>
						<ProfilCommercialContrat>
							<CodeProfilCommercialContrat>String</CodeProfilCommercialContrat>
							<DateDebutValidite>1967-08-13</DateDebutValidite>
							<DateFinValidite>1967-08-13</DateFinValidite>
							<DonneeComplementaire>String</DonneeComplementaire>
							<DonneeComplementaire>String</DonneeComplementaire>
							<Proprietaire>
								<Nom>normalizedString</Nom>
								<IdPartenaire>1</IdPartenaire>
								<CodePays>000</CodePays>
								<CodeBassin>000</CodeBassin>
							</Proprietaire>
						</ProfilCommercialContrat>
						<ClientDetenteur>
							<IdClient>1</IdClient>
							<Nom>normalizedString</Nom>
							<Prenom>normalizedString</Prenom>
							<Titre>1</Titre>
							<DateNaissance>1967-08-13</DateNaissance>
							<TelephonePrive>normalizedString</TelephonePrive>
							<TelephoneTravail>normalizedString</TelephoneTravail>
							<Adresse>
								<NumVoie>String</NumVoie>
								<TypeVoie>String</TypeVoie>
								<LibelleVoie>String</LibelleVoie>
								<LigneAdresse>
									<NumLigne>1</NumLigne>
									<TexteLigne>aaaaaaaaaaaaaaaaaaaaaaaaaaaaaaaa</TexteLigne>
								</LigneAdresse>
								<LigneAdresse>
									<NumLigne>1</NumLigne>
									<TexteLigne>aaaaaaaaaaaaaaaaaaaaaaaaaaaaaaaa</TexteLigne>
								</LigneAdresse>
								<CodePostal>String</CodePostal>
								<CodePays>000</CodePays>
							</Adresse>
							<AdresseTravail>
								<NumVoie>String</NumVoie>
								<TypeVoie>String</TypeVoie>
								<LibelleVoie>String</LibelleVoie>
								<LigneAdresse>
									<NumLigne>1</NumLigne>
									<TexteLigne>aaaaaaaaaaaaaaaaaaaaaaaaaaaaaaaa</TexteLigne>
								</LigneAdresse>
								<LigneAdresse>
									<NumLigne>1</NumLigne>
									<TexteLigne>aaaaaaaaaaaaaaaaaaaaaaaaaaaaaaaa</TexteLigne>
								</LigneAdresse>
								<CodePostal>String</CodePostal>
								<CodePays>000</CodePays>
							</AdresseTravail>
							<CommunicationDonneesPersonnelles>true</CommunicationDonneesPersonnelles>
							<DateSaisie>1967-08-13</DateSaisie>
							<ProfilClient>
								<CodeProfil>1</CodeProfil>
								<DateDebutValiditeProfil>1967-08-13</DateDebutValiditeProfil>
								<DateFinValiditeProfil>1967-08-13</DateFinValiditeProfil>
								<CategorieSociale>String</CategorieSociale>
								<NiveaudEtudes>String</NiveaudEtudes>
								<Profession>String</Profession>
								<Sexe>String</Sexe>
								<TranchedAge>String</TranchedAge>
							</ProfilClient>
							<ProfilClient>
								<CodeProfil>1</CodeProfil>
								<DateDebutValiditeProfil>1967-08-13</DateDebutValiditeProfil>
								<DateFinValiditeProfil>1967-08-13</DateFinValiditeProfil>
								<CategorieSociale>String</CategorieSociale>
								<NiveaudEtudes>String</NiveaudEtudes>
								<Profession>String</Profession>
								<Sexe>String</Sexe>
								<TranchedAge>String</TranchedAge>
							</ProfilClient>
							<PartenaireReferent>
								<Nom>normalizedString</Nom>
								<IdPartenaire>1</IdPartenaire>
								<CodePays>000</CodePays>
								<CodeBassin>000</CodeBassin>
							</PartenaireReferent>
						</ClientDetenteur>
					</ContratProduit>
				</ProduitInstalle>
			</AncienObjetImplique>
		</OperationVente>
	</ListeAcquisition>
</IBACBP:MessageAcquisitions>
